cnuts/__init__.py
cnuts/juice.py
cnuts-0.0.3.dist-info/METADATA
cnuts-0.0.3.dist-info/WHEEL
cnuts-0.0.3.dist-info/top_level.txt
cnuts-0.0.3.dist-info/RECORD
